craft_documents/__init__.py
craft_documents/common/DiskRepresentable.py
craft_documents/common/Exercise.py
craft_documents/common/File.py
craft_documents/common/Folder.py
craft_documents/common/Header.py
craft_documents/common/Preamble.py
craft_documents/common/Prompt.py
craft_documents/common/Prompter.py
craft_documents/common/Template.py
craft_documents/common/TexTemplate.py
craft_documents/common/helpers.py
craft_documents/configuration/AllowEvalValidator.py
craft_documents/configuration/Configuration.py
craft_documents/configuration/CraftExercisesValidator.py
craft_documents/configuration/DocumentNameValidator.py
craft_documents/configuration/HeaderValidator.py
craft_documents/configuration/MultipleExercisesValidator.py
craft_documents/configuration/PreambleValidator.py
craft_documents/configuration/RemoveCommentsValidator.py
craft_documents/configuration/Semantic.py
craft_documents/configuration/TokensValidator.py
craft_documents/configuration/UniqueExercisePlaceholdersValidator.py
craft_documents/configuration/Validator.py
craft_documents/configuration/VerboseValidator.py
craft_documents/debug/Debugger.py
craft_documents/debug/main.py
craft_documents/main.py
craft_documents/new/Compiler.py
craft_documents/new/Subcommands.py
craft_documents/new/Validators.py
craft_documents/new/main.py
craft_documents/templates/TemplateManager.py
craft_documents/templates/fetch.py
craft_documents/templates/list.py
craft_documents/templates/main.py
craft_documents/templates/new/main.py
craft_documents-0.1.4.dist-info/METADATA
craft_documents-0.1.4.dist-info/WHEEL
craft_documents-0.1.4.dist-info/entry_points.txt
craft_documents-0.1.4.dist-info/RECORD
